mcunet/__init__.py
mcunet/model_zoo.py
mcunet/tinynas/__init__.py
mcunet/tinynas/elastic_nn/__init__.py
mcunet/tinynas/elastic_nn/modules/__init__.py
mcunet/tinynas/elastic_nn/modules/dynamic_layers.py
mcunet/tinynas/elastic_nn/modules/dynamic_op.py
mcunet/tinynas/elastic_nn/networks/__init__.py
mcunet/tinynas/elastic_nn/networks/ofa_proxyless.py
mcunet/tinynas/nn/__init__.py
mcunet/tinynas/nn/modules/__init__.py
mcunet/tinynas/nn/modules/layers.py
mcunet/tinynas/nn/networks/__init__.py
mcunet/tinynas/nn/networks/mobilenet_v2.py
mcunet/tinynas/nn/networks/proxyless_nets.py
mcunet/tinynas/tf_codebase/__init__.py
mcunet/tinynas/tf_codebase/generate_tflite.py
mcunet/tinynas/tf_codebase/tf_layers.py
mcunet/tinynas/tf_codebase/tf_model_zoo.py
mcunet/tinynas/tf_codebase/tf_modules.py
mcunet/utils/__init__.py
mcunet/utils/bn_utils.py
mcunet/utils/common_tools.py
mcunet/utils/my_modules.py
mcunet/utils/net_config.py
mcunet/utils/pytorch_modules.py
mcunet/utils/pytorch_utils.py
mcunet-0.1.1.post202206170200.dist-info/LICENSE
mcunet-0.1.1.post202206170200.dist-info/METADATA
mcunet-0.1.1.post202206170200.dist-info/WHEEL
mcunet-0.1.1.post202206170200.dist-info/top_level.txt
mcunet-0.1.1.post202206170200.dist-info/zip-safe
mcunet-0.1.1.post202206170200.dist-info/RECORD
