Metadata-Version: 2.1
Name: mcunet
Version: 0.1.1-202206170200
Summary: MCUNet: Tiny Deep Learning on IoT Devices
Home-page: https://github.com/mit-han-lab/mcunet
Author: MTI HAN LAB 
Author-email: hanlab.eecs+github@gmail.com
License: MIT
Classifier: Programming Language :: Python :: 3
License-File: LICENSE
Requires-Dist: torch
Requires-Dist: torchvision
